dress/__init__.py
dress/config.py
dress/dists.py
dress/plotutils.py
dress/relkin.py
dress/relscatt.py
dress/sampler.py
dress/spec.py
dress/utils.py
dress/vec_ops.py
dress/volspec.py
"dress/data/cross-sections/Be9(He3,n)C11-cross-section_jsi.txt"
"dress/data/cross-sections/Be9(alpha,n)C12-cross-section_jsi.txt"
"dress/data/cross-sections/Be9(alpha,n)C12E1-cross-section.txt"
"dress/data/cross-sections/Be9(d,n)B10-cross-section_jsi.txt"
"dress/data/cross-sections/Be9(p,alpha)Li6-cross-section_jsi.txt"
"dress/data/cross-sections/Be9(p,d)Be8-cross-section_jsi.txt"
"dress/data/cross-sections/Be9(p,n)B9-cross-section_jsi.txt"
"dress/data/cross-sections/T(p,n)He3-cross-section.txt"
"dress/data/cross-sections/T(t,2n)He4-cross-section.txt"
dress/data/cross-sections/alphad-cross-section.txt
dress/data/cross-sections/alphat-cross-section.txt
dress/data/cross-sections/ddn3he_legendre_endf.txt
dress/reactions/__init__.py
dress/reactions/alpha_be9_n_c12_reaction.py
dress/reactions/alpha_be9_n_c12e1_reaction.py
dress/reactions/alpha_scat.py
dress/reactions/d_be9_n_b10_reaction.py
dress/reactions/d_d_n_he3_reaction.py
dress/reactions/d_he3_p_he4_reaction.py
dress/reactions/d_t_n_he4_reaction.py
dress/reactions/masses.py
dress/reactions/p_be9_alpha_li6_reaction.py
dress/reactions/p_be9_d_be8_reaction.py
dress/reactions/p_be9_n_b9_reaction.py
dress/reactions/p_t_n_he3_reaction.py
dress/reactions/particle.py
dress/reactions/reaction.py
dress/reactions/t_t_2n_he4_reaction.py
dress/tokamak/__init__.py
dress/tokamak/tokadist.py
dress/tokamak/tokapart.py
dress/tokamak/utils.py
pydress-1.0.dist-info/LICENSE
pydress-1.0.dist-info/METADATA
pydress-1.0.dist-info/WHEEL
pydress-1.0.dist-info/top_level.txt
pydress-1.0.dist-info/RECORD
