Metadata-Version: 2.1
Name: pydress
Version: 1.0
Summary: Directional Relativistic Spectrum Simulator
Author: Jacob Eriksson, Sean Conroy
Project-URL: Homepage, https://github.com/jacob-eri/pydress
Project-URL: Bug Tracker, https://github.com/jacob-eri/pydress/issues
Keywords: python,fusion
Classifier: Programming Language :: Python :: 3
Classifier: License :: OSI Approved :: MIT License
Classifier: Operating System :: OS Independent
Classifier: Intended Audience :: Science/Research
Requires-Python: >=3.0
License-File: LICENSE
Requires-Dist: numpy
Requires-Dist: scipy
